mold/VERSION
mold/__init__.py
mold/__main__.py
mold/config.py
mold/hook.py
mold/template.py
mold/things.py
mold/cli/__init__.py
mold/cli/configure.py
mold/cli/generate.py
mold/cli/prefill.py
mold/configs/python-library.config.json
mold/configs/python-project.config.json
mold/doc/__init__.py
mold/doc/category.rst.temp
mold/doc/domain.rst.temp
mold/doc/interface.rst.temp
mold/doc/tool.rst.temp
mold/plugins/__init__.py
mold/plugins/categories.py
mold/plugins/domains.py
mold/plugins/face/__init__.py
mold/plugins/face/build.py
mold/plugins/face/doc.py
mold/plugins/face/doc_host.py
mold/plugins/face/github.py
mold/plugins/face/gitignore.py
mold/plugins/face/license.py
mold/plugins/face/package_readme.py
mold/plugins/face/read_the_docs.py
mold/plugins/face/readme.py
mold/plugins/face/source.py
mold/plugins/face/todo.py
mold/plugins/face/vcs_host.py
mold/plugins/tools/__init__.py
mold/plugins/tools/contributing_py_github/__init__.py
mold/plugins/tools/contributing_py_github/templates/contributing.rst.temp
mold/plugins/tools/github/__init__.py
mold/plugins/tools/github/templates/.github/PULL_REQUEST_TEMPLATE.md.temp
mold/plugins/tools/github/templates/.github/ISSUE_TEMPLATE/bug.md.temp
mold/plugins/tools/github/templates/.github/ISSUE_TEMPLATE/config.yml.temp
mold/plugins/tools/github/templates/.github/ISSUE_TEMPLATE/feature.md.temp
mold/plugins/tools/github_actions/__init__.py
mold/plugins/tools/github_actions/templates/.github/workflows/CI.yml.temp
mold/plugins/tools/gitignore_minimal/__init__.py
mold/plugins/tools/gitignore_minimal/templates/.gitignore.temp
mold/plugins/tools/gitignore_python/__init__.py
mold/plugins/tools/gitignore_python/templates/.gitignore.temp
mold/plugins/tools/license_apache_2/__init__.py
mold/plugins/tools/license_apache_2/templates/LICENSE.temp
mold/plugins/tools/license_bsd_3/__init__.py
mold/plugins/tools/license_bsd_3/templates/LICENSE.temp
mold/plugins/tools/license_gpl_3/__init__.py
mold/plugins/tools/license_gpl_3/templates/LICENSE.temp
mold-0.2.3.dist-info/LICENSE
mold-0.2.3.dist-info/METADATA
mold-0.2.3.dist-info/WHEEL
mold-0.2.3.dist-info/entry_points.txt
mold-0.2.3.dist-info/top_level.txt
mold-0.2.3.dist-info/RECORD
