Metadata-Version: 2.1
Name: mold
Version: 0.2.3
Summary: Package / repository initialisation
Home-page: https://pymold.rtfd.org
Author: Felix Hildén
Author-email: felix.hilden@gmail.com
Maintainer: Felix Hildén
Maintainer-email: felix.hilden@gmail.com
License: MIT
Download-URL: https://pypi.org/project/mold
Project-URL: Source, https://github.com/felix-hilden/mold
Project-URL: Issues, https://github.com/felix-hilden/mold/issues
Project-URL: Documentation, https://pymold.rtfd.org
Keywords: package repository template initialisation
Platform: UNKNOWN
Classifier: Development Status :: 4 - Beta
Classifier: Intended Audience :: Developers
Classifier: License :: OSI Approved :: MIT License
Classifier: Programming Language :: Python :: 3
Classifier: Programming Language :: Python :: 3 :: Only
Classifier: Programming Language :: Python :: 3.7
Classifier: Programming Language :: Python :: 3.8
Classifier: Programming Language :: Python :: 3.9
Classifier: Topic :: Software Development :: Build Tools
Classifier: Topic :: Software Development :: Code Generators
Classifier: Topic :: Software Development :: Documentation
Classifier: Topic :: Software Development :: Testing
Requires-Python: >=3.7
License-File: LICENSE
Requires-Dist: Jinja2
Provides-Extra: build
Requires-Dist: build ; extra == 'build'
Requires-Dist: twine ; extra == 'build'
Provides-Extra: checks
Requires-Dist: tox ; extra == 'checks'
Requires-Dist: doc8 (>=0.9) ; extra == 'checks'
Requires-Dist: flake8 ; extra == 'checks'
Requires-Dist: flake8-bugbear ; extra == 'checks'
Requires-Dist: pydocstyle[toml] (>=6.1) ; extra == 'checks'
Requires-Dist: pygments ; extra == 'checks'
Provides-Extra: dev
Requires-Dist: build ; extra == 'dev'
Requires-Dist: twine ; extra == 'dev'
Requires-Dist: sphinx (>=4) ; extra == 'dev'
Requires-Dist: sphinx-rtd-theme ; extra == 'dev'
Requires-Dist: coverage[toml] (>=5) ; extra == 'dev'
Requires-Dist: pytest (>=6) ; extra == 'dev'
Requires-Dist: tox ; extra == 'dev'
Requires-Dist: doc8 (>=0.9) ; extra == 'dev'
Requires-Dist: flake8 ; extra == 'dev'
Requires-Dist: flake8-bugbear ; extra == 'dev'
Requires-Dist: pydocstyle[toml] (>=6.1) ; extra == 'dev'
Requires-Dist: pygments ; extra == 'dev'
Provides-Extra: docs
Requires-Dist: sphinx (>=4) ; extra == 'docs'
Requires-Dist: sphinx-rtd-theme ; extra == 'docs'
Provides-Extra: tests
Requires-Dist: coverage[toml] (>=5) ; extra == 'tests'
Requires-Dist: pytest (>=6) ; extra == 'tests'
